{
    "unstable": {
        "branch": "nixos-unstable",
        "description": "Nix Packages collection",
        "homepage": null,
        "owner": "NixOS",
        "repo": "nixpkgs",
        "rev": "84917aa00bf23c88e5874c683abe05edb0ba4078",
        "sha256": "1x3qh815d7k9yc72zpn5cfaaq2b1942q4pka6rx8b5i33yz4m61q",
        "type": "tarball",
        "url": "https://github.com/NixOS/nixpkgs/archive/84917aa00bf23c88e5874c683abe05edb0ba4078.tar.gz",
        "url_template": "https://github.com/<owner>/<repo>/archive/<rev>.tar.gz"
    }
}
